qbusmqttapi/__init__.py
qbusmqttapi/const.py
qbusmqttapi/discovery.py
qbusmqttapi/factory.py
qbusmqttapi/py.typed
qbusmqttapi/state.py
qbusmqttapi-1.4.2.dist-info/METADATA
qbusmqttapi-1.4.2.dist-info/WHEEL
qbusmqttapi-1.4.2.dist-info/licenses/LICENSE
qbusmqttapi-1.4.2.dist-info/RECORD
