Metadata-Version: 2.4
Name: qbusmqttapi
Version: 1.4.2
Summary: MQTT API for Qbus Home Automation.
Project-URL: Homepage, https://github.com/Qbus-iot/qbusmqttapi
Project-URL: Issues, https://github.com/Qbus-iot/qbusmqttapi/issues
Author: thomasddn
Author-email: Koen Schockaert <ks@qbus.be>
License-Expression: MIT
License-File: LICENSE
Classifier: Development Status :: 5 - Production/Stable
Classifier: Environment :: Console
Classifier: Programming Language :: Python :: 3
Requires-Python: >=3.12
Requires-Dist: aiohttp>=3.11.16
Requires-Dist: yarl>=1.18.3
